sketch_image/__init__.py
sketch_image/main.py
sketch_image-0.1.1.dist-info/METADATA
sketch_image-0.1.1.dist-info/WHEEL
sketch_image-0.1.1.dist-info/entry_points.txt
sketch_image-0.1.1.dist-info/licenses/LICENSE
sketch_image-0.1.1.dist-info/RECORD
