Metadata-Version: 2.4
Name: sketch-image
Version: 0.1.1
Summary: Convert images into sketches
Author-email: Shreyam Pokharel <pshreyam@gmail.com>
License-File: LICENSE
Requires-Python: >=3.12
Requires-Dist: click>=8.2.1
Requires-Dist: numpy>=2.3.2
Requires-Dist: opencv-python>=4.11.0.86
